README
setup.py
ltable/__init__.py
ltable/ssindex.py
ltable/ssresult.py
ltable/sstable.py
ltable.egg-info/PKG-INFO
ltable.egg-info/SOURCES.txt
ltable.egg-info/dependency_links.txt
ltable.egg-info/top_level.txt