Metadata-Version: 1.1
Name: ltable
Version: 0.0.1
Summary: lite table, not depden on numpy or sqliteoperations,.. find, filter, group, sort, top, tail ..
Home-page: https://github.com/maxi119/python-ltable
Author: MaxiL
Author-email: maxil@interserv.com.tw
License: UNKNOWN
Download-URL: https://github.com/maxi119/python-ltable
Keywords: lightning table
Platform: UNKNOWN
Classifier: Development Status :: 1 - Planning
Classifier: Intended Audience :: Developers
Classifier: License :: OSI Approved :: Python Software Foundation License
Classifier: Programming Language :: Python
Classifier: Topic :: Software Development :: Libraries :: Python Modules
